coverage_sh/__init__.py
coverage_sh/plugin.py
coverage_sh-0.4.5.dist-info/METADATA
coverage_sh-0.4.5.dist-info/WHEEL
coverage_sh-0.4.5.dist-info/licenses/LICENSE.txt
coverage_sh-0.4.5.dist-info/RECORD
