Metadata-Version: 2.3
Name: coverage-sh
Version: 0.4.5
Summary: A  Coverage.py plugin to measure code coverage of shell scripts from python.
Project-URL: homepage, https://github.com/lackhove/coverage-sh
Author-email: Kilian Lackhove <kilian@lackhove.de>
License: MIT
License-File: LICENSE.txt
Keywords: bash,coverage,plugin,sh,shell
Classifier: Development Status :: 2 - Pre-Alpha
Classifier: License :: OSI Approved :: MIT License
Classifier: Programming Language :: Python :: 3.8
Classifier: Programming Language :: Python :: 3.9
Classifier: Programming Language :: Python :: 3.10
Classifier: Programming Language :: Python :: 3.11
Classifier: Programming Language :: Python :: 3.12
Classifier: Typing :: Typed
Requires-Python: >=3.8
Requires-Dist: coverage>=7.3.3
Requires-Dist: python-magic>=0.4.27
Requires-Dist: tree-sitter-languages>=1.8.0
